{
    "openapi": "3.0.1",
    "info": {
        "title": "PhoneNumberLookup",
        "description": "Aprovide carrier information for a telephone number or batch of telephone numbers. Currently supports lookups of telephone numbers in the mainland United States, Alaska, Hawaii, District of Columbia, and the provinces of Canada. Telephone numbers submitted must be in E.164 format to be processed.\n## Base Path\n<code>https://numbers.bandwidth.com/api/v1</code>",
        "contact": {},
        "version": "1.0.7",
        "x-server-configuration": {
            "default-environment": "production",
            "default-server": "default",
            "environments": [
                {
                    "name": "production",
                    "servers": [
                        {
                            "name": "default",
                            "url": "https://numbers.bandwidth.com/api/v1"
                        }
                    ]
                },
                {
                    "name": "custom",
                    "servers": [
                        {
                            "name": "default",
                            "url": "{base_url}"
                        }
                    ]
                }
            ],
            "parameters": [
                {
                    "name": "base_url",
                    "description": "",
                    "type": "string",
                    "example": "https://www.example.com"
                }
            ]
        }
    },
    "components": {
        "securitySchemes": {
            "httpBasic": {
                "type": "http",
                "scheme": "basic"
            }
        },
        "schemas": {
            "OrderRequest": {
                "title": "OrderRequest",
                "type": "object",
                "properties": {
                    "tns": {
                        "type": "array",
                        "items": {
                            "type": "string"
                        }
                    }
                },
                "x-examples": {
                    "One TN": {
                        "tns": [
                            "19196104420"
                        ]
                    },
                    "Multiple TNs": {
                        "tns": [
                            "19196104420",
                            "+19196104424"
                        ]
                    }
                },
                "description": "Create TN Lookup Request"
            },
            "OrderResponse": {
                "title": "OrderResponse",
                "type": "object",
                "properties": {
                    "requestId": {
                        "type": "string"
                    },
                    "status": {
                        "type": "string"
                    }
                },
                "x-examples": {
                    "Response Example": {
                        "requestId": "004223a0-8b17-41b1-bf81-20732adf5590",
                        "status": "IN_PROGRESS"
                    }
                },
                "description": "The request has been accepted for processing but not yet finished and in a terminal state (COMPLETE, PARTIAL_COMPLETE, or FAILED)"
            },
            "OrderStatus": {
                "properties": {
                    "requestId": {
                        "type": "string",
                        "description": "The requestId."
                    },
                    "status": {
                        "type": "string",
                        "description": "The status of the request (IN_PROGRESS, COMPLETE, PARTIAL_COMPLETE, or FAILED)."
                    },
                    "failedTelephoneNumbers": {
                        "type": "array",
                        "description": "The telephone numbers whose lookup failed",
                        "items": {
                            "type": "string"
                        }
                    },
                    "result": {
                        "type": "array",
                        "description": "The carrier information results for the specified telephone number.",
                        "items": {
                            "type": "object",
                            "properties": {
                                "Response Code": {
                                    "type": "integer",
                                    "description": "Our vendor's response code."
                                },
                                "Message": {
                                    "type": "string",
                                    "description": "Message associated with the response code."
                                },
                                "E.164 Format": {
                                    "type": "string",
                                    "description": "The telephone number in E.164 format."
                                },
                                "Formatted": {
                                    "type": "string",
                                    "description": "The formatted version of the telephone number."
                                },
                                "Country": {
                                    "type": "string",
                                    "description": "The country of the telephone number."
                                },
                                "Line Type": {
                                    "type": "string",
                                    "description": "The line type of the telephone number."
                                },
                                "Line Provider": {
                                    "type": "string",
                                    "description": "The service provider of the telephone number."
                                },
                                "Mobile Country Code": {
                                    "type": "string",
                                    "description": "The first half of the Home Network Identity (HNI)."
                                },
                                "Mobile Network Code": {
                                    "type": "string",
                                    "description": "The second half of the HNI."
                                }
                            }
                        }
                    }
                },
                "description": "If requestId exists, the result for that request is returned. See the Examples for details on the various responses that you can receive.  Generally, if you see a Response Code of 0 in a result for a TN, information will be available for it.  Any other Response Code will indicate no information was available for the TN.",
                "title": ""
            }
        }
    },
    "security": [
        {
            "httpBasic": []
        }
    ],
    "paths": {
        "/accounts/{accountId}/tnlookup": {
            "post": {
                "summary": "Create Request",
                "description": "Create a TN Lookup Order.",
                "operationId": "LookupRequest",
                "tags": [
                    "Phone Number Lookup"
                ],
                "parameters": [
                    {
                        "name": "accountId",
                        "description": "The ID of the Bandwidth account that the user belongs to.",
                        "in": "path",
                        "required": true,
                        "schema": {
                            "type": "string",
                            "format": "1-7 digits",
                            "example": "9998887"
                        }
                    }
                ],
                "requestBody": {
                    "content": {
                        "application/json": {
                            "schema": {
                                "$ref": "#/components/schemas/OrderRequest"
                            },
                            "examples": {
                                "One TN": {
                                    "value": {
                                        "tns": [
                                            "19196104420"
                                        ]
                                    }
                                },
                                "Multiple Tns": {
                                    "value": {
                                        "tns": [
                                            "19196104420",
                                            "+19196104424"
                                        ]
                                    }
                                }
                            }
                        }
                    },
                    "required": true
                },
                "responses": {
                    "202": {
                        "description": "The request has been accepted for processing but not yet finished and in a terminal state (COMPLETE, PARTIAL_COMPLETE, or FAILED)",
                        "content": {
                            "application/json": {
                                "schema": {
                                    "$ref": "#/components/schemas/OrderResponse"
                                },
                                "examples": {
                                    "Order Response": {
                                        "value": {
                                            "requestId": "004223a0-8b17-41b1-bf81-20732adf5590",
                                            "status": "IN_PROGRESS"
                                        }
                                    }
                                }
                            }
                        }
                    },
                    "400": {
                        "description": "Bad Request. Ensure that your request payload is properly formatted and that the telephone numbers used are valid.",
                        "content": {
                            "application/json": {
                                "example": {
                                    "message": "The following numbers are not supported. Only US (United States) and CA (Canada) number lookups are supported at this time: +1200207163, 12002077164, 12002077165"
                                },
                                "schema": {
                                    "properties": {
                                        "message": {
                                            "type": "string",
                                            "description": "A description of what validation error occurred."
                                        }
                                    }
                                }
                            }
                        }
                    },
                    "401": {
                        "description": "Unauthorized. Ensure that you are using the proper credentials for the environment you are accessing, your user has the proper role assigned to it, and that your Bandwidth account is enabled for TN Lookup access."
                    },
                    "415": {
                        "description": "Invalid content-type. Ensure that your content-type header is set to application/json."
                    },
                    "429": {
                        "description": "Too Many Requests. Reduce the amount of requests that you are sending in order to avoid receiving this status code."
                    },
                    "5XX": {
                        "description": "Unexpected error. Please contact Bandwidth Support if your requests are receiving this status code for an extended period of time."
                    }
                },
                "x-codeSamples": [
                    {
                        "lang": "cURL",
                        "source": "curl 'https://numbers.bandwidth.com/api/v1/accounts/12345/tnlookup' \\\r\n    -X POST \\\r\n    -H 'Authorization: Basic dXNlcm5hbWU6cGFzc3dvcmQ=' \\\r\n    -H 'Content-Type: application/json' \\\r\n    -d '{\r\n        \"tns\":\r\n        [\r\n            \"19196104420\"\r\n        ]\r\n    }'\r\n"
                    },
                    {
                        "lang": "C#",
                        "source": "using System;\r\nusing System.Collections.Generic;\r\nusing System.Threading.Tasks;\r\nusing Bandwidth.Standard;\r\nusing Bandwidth.Standard.Exceptions;\r\nusing Bandwidth.Standard.PhoneNumberLookup.Models;\r\n\r\nclass Program\r\n{\r\n    static async Task Main(string[] args)\r\n    {\r\n        var username = \"api-username\";\r\n        var password = \"api-pasword\";\r\n        var accountId = \"12345\";\r\n\r\n        var client = new BandwidthClient.Builder()\r\n            .PhoneNumberLookupBasicAuthCredentials(username, password)\r\n            .Build();\r\n\r\n        var request = new OrderRequest\r\n        {\r\n            Tns = new List<string> { \"+15553334444\" }\r\n        };\r\n\r\n        try\r\n        {\r\n            var response = await client.PhoneNumberLookup.APIController.CreateLookupRequestAsync(accountId, request);\r\n            Console.WriteLine(response.Data);\r\n        }\r\n        catch (ApiException e)\r\n        {\r\n            Console.WriteLine(e.Message);\r\n        }\r\n    }\r\n}\r\n"
                    },
                    {
                        "lang": "Java",
                        "source": "import com.bandwidth.BandwidthClient;\r\nimport com.bandwidth.http.response.ApiResponse;\r\nimport com.bandwidth.phonenumberlookup.models.OrderRequest;\r\nimport com.bandwidth.phonenumberlookup.models.OrderResponse;\r\n\r\nimport java.util.concurrent.CompletableFuture;\r\nimport java.util.concurrent.ExecutionException;\r\nimport java.util.ArrayList;\r\nimport java.util.List;\r\n\r\npublic class Sample {\r\n    public static final String USERNAME = \"api-username\";\r\n    public static final String PASSWORD = \"api-password\";\r\n    public static final String ACCOUNT_ID = \"12345\";\r\n\r\n    public static void main(String[] args) {\r\n        BandwidthClient client = new BandwidthClient.Builder()\r\n                .phoneNumberLookupBasicAuthCredentials(USERNAME, PASSWORD)\r\n                .build();\r\n\r\n        List<String> numbers = new ArrayList<>();\r\n        numbers.add(\"+15553334444\");\r\n\r\n        OrderRequest request = new OrderRequest(numbers);\r\n\r\n        try {\r\n            CompletableFuture<ApiResponse<OrderResponse>> completableFuture = client.getPhoneNumberLookupClient().getAPIController().createLookupRequestAsync(ACCOUNT_ID, request);\r\n            System.out.println(completableFuture.get().getResult());\r\n        } catch (InterruptedException | ExecutionException e) {\r\n            System.out.println(e.getMessage());\r\n        }\r\n    }\r\n}\r\n"
                    },
                    {
                        "lang": "PHP",
                        "source": "<?php\r\n\r\nrequire \"vendor/autoload.php\";\r\n\r\napi-username = \"api-username\";\r\napi-password = \"api-pasword\";\r\n12345 = \"12345\";\r\n\r\n$config = new BandwidthLib\\Configuration(\r\n    array(\r\n        'messagingBasicAuthUserName' => $BW_USERNAME,\r\n        'messagingBasicAuthPassword' => $BW_PASSWORD,\r\n    )\r\n);\r\n$client = new BandwidthLib\\BandwidthClient($config);\r\n\r\n$phoneNumberLookupClient = $client->getPhoneNumberLookup()->getClient();\r\n\r\n$body = new BandwidthLib\\PhoneNumberLookup\\Models\\OrderRequest();\r\n$body->tns = array(\"+15554443333\");\r\n\r\ntry {\r\n    $response = $phoneNumberLookupClient->createLookupRequest($BW_ACCOUNT_ID, $body);\r\n    print_r($response->getResult()->requestId);\r\n} catch (BandwidthLib\\APIException $e) {\r\n    print_r($e->getResponseCode());\r\n}\r\n"
                    },
                    {
                        "lang": "Python",
                        "source": "from bandwidth.bandwidth_client import BandwidthClient\r\nfrom bandwidth.exceptions.api_exception import APIException\r\nfrom bandwidth.phonenumberlookup.models.order_request import OrderRequest\r\n\r\nimport os\r\n\r\nBW_USERNAME = \"api-username\"\r\nBW_PASSWORD = \"api-password\"\r\nBW_ACCOUNT_ID = \"12345\"\r\n\r\nbandwidth_client = BandwidthClient(\r\n    phone_number_lookup_basic_auth_user_name=BW_USERNAME,\r\n    phone_number_lookup_basic_auth_password=BW_PASSWORD\r\n)\r\nphone_number_lookup_client = bandwidth_client.phone_number_lookup_client.client\r\n\r\nbody = OrderRequest()\r\nbody.tns = [\"+15554443333\"]\r\n\r\ntry:\r\n    response = phone_number_lookup_client.create_lookup_request(BW_ACCOUNT_ID, body)\r\n    print(response.body.request_id)\r\nexcept APIException as e:\r\n    print(e.response_code)\r\n"
                    },
                    {
                        "lang": "Ruby",
                        "source": "require 'bandwidth'\r\n  \r\ninclude Bandwidth\r\ninclude Bandwidth::Voice\r\n\r\nBW_USERNAME = \"api-username\"\r\nBW_PASSWORD = \"api-password\"\r\nBW_ACCOUNT_ID = \"12345\"\r\n\r\nbandwidth_client = Bandwidth::Client.new(\r\n    phone_number_lookup_basic_auth_user_name: BW_USERNAME,\r\n    phone_number_lookup_basic_auth_password: BW_PASSWORD\r\n)\r\n\r\nphone_number_lookup_client = bandwidth_client.phone_number_lookup_client.client\r\n\r\nbody = OrderRequest.new\r\nbody.tns = [\"+15554443333\"]\r\n\r\nbegin\r\n    result = phone_number_lookup_client.create_lookup_request(BW_ACCOUNT_ID, body)\r\n    puts result.data.request_id\r\nrescue APIException => e\r\n    puts e.response_code\r\nend\r\n"
                    }
                ]
            }
        },
        "/accounts/{accountId}/tnlookup/{requestId}": {
            "get": {
                "summary": "Query Request Status",
                "operationId": "LookupRequestStatus",
                "description": "Query an existing TN Lookup Order.",
                "tags": [
                    "Phone Number Lookup"
                ],
                "parameters": [
                    {
                        "name": "accountId",
                        "description": "The ID of the Bandwidth account that the user belongs to.",
                        "in": "path",
                        "required": true,
                        "schema": {
                            "type": "string",
                            "format": "1-7 digits",
                            "example": "9998887"
                        }
                    },
                    {
                        "name": "requestId",
                        "in": "path",
                        "required": true,
                        "schema": {
                            "type": "string"
                        }
                    }
                ],
                "responses": {
                    "200": {
                        "description": "If requestId exists, the result for that request is returned. See the Examples for details on the various responses that you can receive.  Generally, if you see a Response Code of 0 in a result for a TN, information will be available for it.  Any other Response Code will indicate no information was available for the TN.",
                        "content": {
                            "application/json": {
                                "examples": {
                                    "IN_PROGRESS Status": {
                                        "value": {
                                            "requestId": "004223a0-8b17-41b1-bf81-20732adf5590",
                                            "status": "IN_PROGRESS"
                                        }
                                    },
                                    "One TN - COMPLETE Status": {
                                        "value": {
                                            "requestId": "004223a0-8b17-41b1-bf81-20732adf5590",
                                            "status": "COMPLETE",
                                            "result": [
                                                {
                                                    "Response Code": 0,
                                                    "Message": "NOERROR",
                                                    "E.164 Format": "19196104424",
                                                    "Formatted": "(919) 610-4424",
                                                    "Country": "US",
                                                    "Line Type": "Mobile",
                                                    "Line Provider": "T-Mobile USA",
                                                    "Mobile Country Code": "310",
                                                    "Mobile Network Code": "160"
                                                }
                                            ]
                                        }
                                    },
                                    "Multiple TNs - COMPLETE Status": {
                                        "value": {
                                            "requestId": "004223a0-8b17-41b1-bf81-20732adf5590",
                                            "status": "COMPLETE",
                                            "result": [
                                                {
                                                    "Response Code": 0,
                                                    "Message": "NOERROR",
                                                    "E.164 Format": "+19196104424",
                                                    "Formatted": "(919) 610-4424",
                                                    "Country": "US",
                                                    "Line Type": "Mobile",
                                                    "Line Provider": "T-Mobile USA",
                                                    "Mobile Country Code": "310",
                                                    "Mobile Network Code": "160"
                                                },
                                                {
                                                    "Response Code": 0,
                                                    "Message": "NOERROR",
                                                    "E.164 Format": "19196100",
                                                    "Formatted": "(919) 610-4420",
                                                    "Country": "US",
                                                    "Line Type": "Mobile",
                                                    "Line Provider": "Verizon Wireless",
                                                    "Mobile Country Code": "310",
                                                    "Mobile Network Code": "010"
                                                }
                                            ]
                                        }
                                    },
                                    "Multiple TNs - PARTIAL_COMPLETE Status": {
                                        "value": {
                                            "requestId": "004223a0-8b17-41b1-bf81-20732adf5590",
                                            "status": "PARTIAL_COMPLETE",
                                            "result": [
                                                {
                                                    "Response Code": 0,
                                                    "Message": "NOERROR",
                                                    "E.164 Format": "+19196104424",
                                                    "Formatted": "(919) 610-4424",
                                                    "Country": "US",
                                                    "Line Type": "Mobile",
                                                    "Line Provider": "T-Mobile USA",
                                                    "Mobile Country Code": "310",
                                                    "Mobile Network Code": "160"
                                                }
                                            ],
                                            "failedTelephoneNumbers": [
                                                "+13992077164"
                                            ]
                                        }
                                    },
                                    "COMPLETE Status But No Information on a TN": {
                                        "value": {
                                            "requestId": "004223a0-8b17-41b1-bf81-20732adf5590",
                                            "status": "COMPLETE",
                                            "result": [
                                                {
                                                    "Response Code": 3,
                                                    "Message": "NXDOMAIN",
                                                    "E.164 Format": "19196104425",
                                                    "Formatted": "(919) 610-4425",
                                                    "Country": "US"
                                                }
                                            ]
                                        }
                                    },
                                    "FAILED Status": {
                                        "value": {
                                            "requestId": "004223a0-8b17-41b1-bf81-20732adf5590",
                                            "status": "FAILED",
                                            "failedTelephoneNumbers": [
                                                "+13992077164"
                                            ]
                                        }
                                    }
                                },
                                "schema": {
                                    "$ref": "#/components/schemas/OrderStatus"
                                }
                            }
                        }
                    },
                    "400": {
                        "description": "Bad Request. Ensure that you have set the requestId as a URL path parameter."
                    },
                    "401": {
                        "description": "Unauthorized. Ensure that you are using the proper credentials for the environment you are accessing, your user has the proper role assigned to it, and that your Bandwidth account is enabled for TN Lookup access."
                    },
                    "404": {
                        "description": "RequestId not found. Ensure that the requestId used in the URL path is valid and maps to a previous request that was submitted."
                    },
                    "429": {
                        "description": "Too Many Requests. Reduce the amount of requests that you are sending in order to avoid receiving this status code."
                    },
                    "5XX": {
                        "description": "Unexpected error. Please contact Bandwidth Support if your requests are receiving this status code for an extended period of time."
                    }
                },
                "x-codeSamples": [
                    {
                        "lang": "cURL",
                        "source": "curl 'https://numbers.bandwidth.com/api/v1/accounts/12345/tnlookup/004223a0-8b17-41b1-bf81-20732adf5590' \\\r\n    -H 'Authorization: Basic dXNlcm5hbWU6cGFzc3dvcmQ='\r\n"
                    },
                    {
                        "lang": "C#",
                        "source": "using System;\r\nusing System.Collections.Generic;\r\nusing System.Threading.Tasks;\r\nusing Bandwidth.Standard;\r\nusing Bandwidth.Standard.Exceptions;\r\n\r\nclass Program\r\n{\r\n    static async Task Main(string[] args)\r\n    {\r\n        var username = \"api-username\";\r\n        var password = \"api-pasword\";\r\n        var accountId = \"12345\";\r\n\r\n        var client = new BandwidthClient.Builder()\r\n            .PhoneNumberLookupBasicAuthCredentials(username, password)\r\n            .Build();\r\n\r\n        var requestId = \"8a358296-e188-4a3a-b974-8e4d12001dd8\";\r\n\r\n        try\r\n        {\r\n            var response = await client.PhoneNumberLookup.APIController.GetLookupRequestStatusAsync(accountId, requestId);\r\n            Console.WriteLine(response.Data);\r\n        }\r\n        catch (ApiException e)\r\n        {\r\n            Console.WriteLine(e.Message);\r\n        }\r\n    }\r\n}\r\n"
                    },
                    {
                        "lang": "Java",
                        "source": "import com.bandwidth.BandwidthClient;\r\nimport com.bandwidth.http.response.ApiResponse;\r\nimport com.bandwidth.phonenumberlookup.models.OrderStatus;\r\n\r\nimport java.util.concurrent.CompletableFuture;\r\nimport java.util.concurrent.ExecutionException;\r\n\r\npublic class Sample {\r\n    public static final String USERNAME = \"api-username\";\r\n    public static final String PASSWORD = \"api-password\";\r\n    public static final String ACCOUNT_ID = \"12345\";\r\n\r\n    public static void main(String[] args) {\r\n        BandwidthClient client = new BandwidthClient.Builder()\r\n                .phoneNumberLookupBasicAuthCredentials(USERNAME, PASSWORD)\r\n                .build();\r\n\r\n        String requestId = \"8a358296-e188-4a3a-b974-8e4d12001dd8\";\r\n\r\n        try {\r\n            CompletableFuture<ApiResponse<OrderStatus>> completableFuture = client.getPhoneNumberLookupClient().getAPIController().getLookupRequestStatusAsync(ACCOUNT_ID, requestId);\r\n            System.out.println(completableFuture.get().getResult());\r\n        } catch (InterruptedException | ExecutionException e) {\r\n            System.out.println(e.getMessage());\r\n        }\r\n    }\r\n}\r\n"
                    },
                    {
                        "lang": "PHP",
                        "source": "<?php\r\n\r\nrequire \"vendor/autoload.php\";\r\n\r\napi-username = \"api-username\";\r\napi-password = \"api-pasword\";\r\n12345 = \"12345\";\r\n\r\n$config = new BandwidthLib\\Configuration(\r\n    array(\r\n        'messagingBasicAuthUserName' => $BW_USERNAME,\r\n        'messagingBasicAuthPassword' => $BW_PASSWORD,\r\n    )\r\n);\r\n$client = new BandwidthLib\\BandwidthClient($config);\r\n\r\n$phoneNumberLookupClient = $client->getPhoneNumberLookup()->getClient();\r\n\r\n$requestId = \"1234-abcd\";\r\n\r\ntry {\r\n    $response = $phoneNumberLookupClient->getLookupRequestStatus($BW_ACCOUNT_ID, $requestId);\r\n    print_r($response->getResult()->status);\r\n} catch (BandwidthLib\\APIException $e) {\r\n    print_r($e->getResponseCode());\r\n}\r\n"
                    },
                    {
                        "lang": "Python",
                        "source": "from bandwidth.bandwidth_client import BandwidthClient\r\nfrom bandwidth.exceptions.api_exception import APIException\r\n\r\nimport os\r\n\r\nBW_USERNAME = \"api-username\"\r\nBW_PASSWORD = \"api-password\"\r\nBW_ACCOUNT_ID = \"12345\"\r\n\r\nbandwidth_client = BandwidthClient(\r\n    phone_number_lookup_basic_auth_user_name=BW_USERNAME,\r\n    phone_number_lookup_basic_auth_password=BW_PASSWORD\r\n)\r\nphone_number_lookup_client = bandwidth_client.phone_number_lookup_client.client\r\n\r\nrequest_id = \"1234-abcd\"\r\n\r\ntry:\r\n    response = phone_number_lookup_client.get_lookup_request_status(BW_ACCOUNT_ID, request_id)\r\n    print(response.body.status)\r\nexcept APIException as e:\r\n    print(e.response_code)\r\n"
                    },
                    {
                        "lang": "Ruby",
                        "source": "require 'bandwidth'\r\n  \r\ninclude Bandwidth\r\ninclude Bandwidth::Voice\r\n\r\nBW_USERNAME = \"api-username\"\r\nBW_PASSWORD = \"api-password\"\r\nBW_ACCOUNT_ID = \"12345\"\r\n\r\nbandwidth_client = Bandwidth::Client.new(\r\n    phone_number_lookup_basic_auth_user_name: BW_USERNAME,\r\n    phone_number_lookup_basic_auth_password: BW_PASSWORD\r\n)\r\n\r\nphone_number_lookup_client = bandwidth_client.phone_number_lookup_client.client\r\n\r\nrequest_id = \"1234-abcd\"\r\n\r\nbegin\r\n    result = phone_number_lookup_client.get_lookup_request_status(BW_ACCOUNT_ID, request_id)\r\n    puts result.data.status\r\nrescue APIException => e\r\n    puts e.response_code\r\nend\r\n"
                    }
                ]
            }
        }
    },
    "servers": [
        {
            "description": "Production",
            "url": "https://numbers.bandwidth.com/api/v1"
        }
    ]
}